LICENSE
MANIFEST.in
README.rst
setup.py
django_trufflehog.egg-info/PKG-INFO
django_trufflehog.egg-info/SOURCES.txt
django_trufflehog.egg-info/dependency_links.txt
django_trufflehog.egg-info/requires.txt
django_trufflehog.egg-info/top_level.txt
trufflehog/__init__.py
trufflehog/managers.py
trufflehog/models.py